microsplit/__init__.py
microsplit/auxiliary.py
microsplit/bam.py
microsplit/fastq.py
microsplit/main.py
microsplit/processmanager.py
microsplit/split.py
microsplit-1.0.1.dist-info/licenses/LICENSE
microsplit-1.0.1.dist-info/METADATA
microsplit-1.0.1.dist-info/WHEEL
microsplit-1.0.1.dist-info/entry_points.txt
microsplit-1.0.1.dist-info/top_level.txt
microsplit-1.0.1.dist-info/RECORD
