Metadata-Version: 2.4
Name: microsplit
Version: 1.0.1
Summary: Preprocess micros-C data for increasing the number of contact identified
Requires-Python: >=3.13
License-File: LICENSE
Requires-Dist: pysam>=0.22.1
Dynamic: license-file
